simple_rec/__init__.py
simple_rec/compute/__init__.py
simple_rec/compute/_similarity.py
simple_rec/compute/_sparse.py
simple_rec/filters/__init__.py
simple_rec/filters/collaborative.py
simple_rec-0.0.1.dist-info/LICENSE
simple_rec-0.0.1.dist-info/METADATA
simple_rec-0.0.1.dist-info/WHEEL
simple_rec-0.0.1.dist-info/top_level.txt
simple_rec-0.0.1.dist-info/RECORD
